srf_weather/__init__.py
srf_weather/main.py
srf_weather/weather.py
srf_weather-0.1.1.dist-info/LICENSE
srf_weather-0.1.1.dist-info/METADATA
srf_weather-0.1.1.dist-info/WHEEL
srf_weather-0.1.1.dist-info/entry_points.txt
srf_weather-0.1.1.dist-info/RECORD
